MANIFEST.in
README.rst
bottle_flash2.py
setup.py
bottle_flash2.egg-info/PKG-INFO
bottle_flash2.egg-info/SOURCES.txt
bottle_flash2.egg-info/dependency_links.txt
bottle_flash2.egg-info/requires.txt
bottle_flash2.egg-info/top_level.txt