Metadata-Version: 1.1
Name: bottle-flash2
Version: 0.0.3
Summary: flash plugin for bottle
Home-page: https://github.com/shinshin86/bottle-flash2
Author: shinshin86
Author-email: beagles1986@gmail.com
License: MIT
Platform: UNKNOWN
Classifier: Framework :: Bottle
Classifier: Programming Language :: Python :: 2
Classifier: Programming Language :: Python :: 2.7
Classifier: Programming Language :: Python :: 3
Classifier: Programming Language :: Python :: 3.5
Classifier: License :: OSI Approved :: MIT License
